zonarPy/__init__.py
zonarPy/ac_basic.py
zonarPy/get_Sv.py
zonarPy/get_bd.py
zonarPy/get_gps.py
zonarPy/get_mlsv.py
zonarPy/help_fun.py
zonarPy/kml2.py
zonarPy/log_update.py
zonarPy/meta_reader.py
zonarPy/plot3d.py
zonarPy/read_sat.py
zonarPy/rho.py
zonarPy/zonar2nc.py
zonarPy/zonar_reader.py
zonarPy-0.0.20.dist-info/LICENSE
zonarPy-0.0.20.dist-info/METADATA
zonarPy-0.0.20.dist-info/WHEEL
zonarPy-0.0.20.dist-info/top_level.txt
zonarPy-0.0.20.dist-info/RECORD
